{
  "msgs":{
    "nl":{
      "blog.article.add.new.button": "Voeg nieuw artikel toe",
      "blog.article.add.first.button": "Voeg eerste artikel toe",
      "blog.drafts.title": "Drafts",
      "blog.article.draft.label": "DRAFT",
      "blog.article.scheduled.label": "gepland",
      "blog.article.publish.button": "Publiceer",
      "blog.article.unpublish.button": "Verbergen",
      "blog.article.remove.button": "Verwijderen",
      "blog.article.remove.confirm": "Ben je zeker dat je dit artikel wilt verwijderen?",
      "blog.article.add.body.button": "Voeg hoofdtekst toe",
      "blog.article.add.type.label": "Type",
      "blog.article.add.title.label": "Titel",
      "blog.article.add.lead.label": "Inleiding",
      "blog.article.add.body.label": "Hoofdtekst",
      "blog.article.add.published.checkbox": "Gepubliceerd",
      "blog.article.add.button": "Opslaan",
      "blog.article.cancel.button": "Annuleren",
      "blog.article.main.language.restriction.message": "Op dit moment kan je nieuwe artikelen enkel in de hoofdtaal toevoegen.",
      "blog.article.default.title":"Dit is de titel van jouw artikel",
      "blog.article.default.lead":"Hier kan je een korte inleiding van het artikel schrijven",
      "blog.article.default.body":"Hier kan je de inhoud van jouw artikel schrijven.",
      "blog.unavailable.message": "Upgrade your website to use our blog feature. Use this to add your articles, projects, teammates or whatever you like!",
      "blog.upgrade.button": "Upgrade",
      "blog.read.more": "Lees meer...",
      "blog.back": "terug naar overzicht",
      "blog.view.all.articles": "Bekijk alle artikelen",
      "blog.publication.time.label": "Publicatietijd",
      "blog.time.violation.format": "Ongeldig formaat"
    }, "en":{
      "blog.article.add.new.button": "Add new article",
      "blog.article.add.first.button": "Add first article",
      "blog.drafts.title": "Drafts",
      "blog.article.draft.label": "DRAFT",
      "blog.article.scheduled.label": "scheduled",
      "blog.article.publish.button": "Publish",
      "blog.article.unpublish.button": "Unpublish",
      "blog.article.remove.button": "Remove",
      "blog.article.remove.confirm": "Are you sure you want to remove this article?",
      "blog.article.add.body.button": "Add body",
      "blog.article.add.type.label": "Type",
      "blog.article.add.title.label": "Title",
      "blog.article.add.lead.label": "Lead",
      "blog.article.add.body.label": "Body",
      "blog.article.add.published.checkbox": "Published",
      "blog.article.add.button": "Save",
      "blog.article.cancel.button": "Cancel",
      "blog.article.main.language.restriction.message": "Currently you can only add new articles in the main language.",
      "blog.article.default.title":"This is the title of your article",
      "blog.article.default.lead":"Here you can write a short lead paragraph for your article",
      "blog.article.default.body":"Here you can write the body of your article",
      "blog.unavailable.message": "Upgrade your website to use our blog feature. Use this to add your articles, projects, teammates or whatever you like!",
      "blog.upgrade.button": "Upgrade",
      "blog.read.more": "Read more...",
      "blog.back": "Back to overview",
      "blog.view.all.articles": "View all articles",
      "blog.publication.time.label": "Publication time",
      "blog.time.violation.format": "Invalid format"
    }, "fr":{
      "blog.article.add.new.button": "Ajouter un nouvel article",
      "blog.article.add.first.button": "Ajouter premier article",
      "blog.drafts.title": "Brouillon",
      "blog.article.draft.label": "BROUILLON",
      "blog.article.scheduled.label": "programmé",
      "blog.article.publish.button": "Publier",
      "blog.article.unpublish.button": "Annuler la publication",
      "blog.article.remove.button": "Supprimer",
      "blog.article.remove.confirm": "Êtes-vous sûr de vouloir supprimer l'article?",
      "blog.article.add.body.button": "Ajouter un article principal",
      "blog.article.add.type.label": "Type",
      "blog.article.add.title.label": "Titre",
      "blog.article.add.lead.label": "Introduction",
      "blog.article.add.body.label": "Texte principal",
      "blog.article.add.published.checkbox": "Publié",
      "blog.article.add.button": "Ajouter",
      "blog.article.cancel.button": "Annuler",
      "blog.article.main.language.restriction.message": "Actuellement, le blog n'est disponible que dans la langue principale.",
      "blog.article.default.title":"Tel est le titre de votre article",
      "blog.article.default.lead":"Ici vous pouvez écrire une courte introduction à l'article",
      "blog.article.default.body":"Ici vous pouvez écrire le contenu de votre article.",
      "blog.unavailable.message": "Mettez à niveau votre site web pour utiliser la fonction de blog. Utilisez ceci pour ajouter vos articles, projets, coéquipiers ou tout ce que vous voulez!",
      "blog.upgrade.button": "Mise à niveau",
      "blog.read.more": "Lire plus...",
      "blog.back": "Retour à la liste",
      "blog.view.all.articles": "Voir tous les articles",
      "blog.publication.time.label": "Temps de publication",
      "blog.time.violation.format": "Format invalide"
    }, "de":{
      "blog.article.add.new.button": "Neuer Artikel",
      "blog.article.add.first.button": "Add first article",
      "blog.drafts.title": "Entwürfe",
      "blog.article.draft.label": "ENTWURF",
      "blog.article.scheduled.label": "scheduled",
      "blog.article.publish.button": "Veröffentlichen",
      "blog.article.unpublish.button": "Verbergen",
      "blog.article.remove.button": "Löschen",
      "blog.article.remove.confirm": "Diesen Artikel wirklich löschen?",
      "blog.article.add.body.button": "Haupttext hinzufügen",
      "blog.article.add.type.label": "Typ",
      "blog.article.add.title.label": "Titel",
      "blog.article.add.lead.label": "Einleitung",
      "blog.article.add.body.label": "Haupttext",
      "blog.article.add.published.checkbox": "Veröffentlicht",
      "blog.article.add.button": "Speichern",
      "blog.article.cancel.button": "Abbrechen",
      "blog.article.main.language.restriction.message": "Currently you can only add new articles in the main language.",
      "blog.article.default.title":"Dies ist der Titel Ihres Artikels",
      "blog.article.default.lead":"Hier können Sie eine kurze Einführung in die Artikel zu schreiben",
      "blog.article.default.body":"Hier können Sie den Inhalt Ihrer Artikel zu schreiben.",
      "blog.unavailable.message": "Upgrade your website to use our blog feature. Use this to add your articles, projects, teammates or whatever you like!",
      "blog.upgrade.button": "Upgrade",
      "blog.read.more": "Mehr lesen...",
      "blog.back": "Zurück zur Übersicht",
      "blog.view.all.articles": "View all articles",
      "blog.publication.time.label": "Publication time",
      "blog.time.violation.format": "Invalid format"
    }
  }
}